{
  "fn_root_make_params_and_execute": "sh2amp",
  "properties": {
    "nonnegative": {
      "var_param": "nonnegative"
    },
    "grad": {
      "var_param": "grad"
    },
    "fslgrad": {
      "var_param": "fslgrad",
      "fn_struct_make_params": "sh2amp_fslgrad_params",
      "properties": {
        "bvecs": {
          "var_param": "bvecs"
        },
        "bvals": {
          "var_param": "bvals"
        }
      }
    },
    "strides": {
      "var_param": "strides",
      "variants": {
        "VariousString": {
          "fn_struct_make_params": "sh2amp_various_string_params",
          "properties": {
            "obj": {
              "var_param": "obj"
            }
          }
        },
        "VariousFile": {
          "fn_struct_make_params": "sh2amp_various_file_params",
          "properties": {
            "obj": {
              "var_param": "obj"
            }
          }
        }
      }
    },
    "datatype": {
      "var_param": "datatype"
    },
    "info": {
      "var_param": "info"
    },
    "quiet": {
      "var_param": "quiet"
    },
    "debug": {
      "var_param": "debug"
    },
    "force": {
      "var_param": "force"
    },
    "nthreads": {
      "var_param": "nthreads"
    },
    "config": {
      "var_param": "config",
      "fn_struct_make_params": "sh2amp_config_params",
      "properties": {
        "key": {
          "var_param": "key"
        },
        "value": {
          "var_param": "value"
        }
      }
    },
    "help": {
      "var_param": "help_"
    },
    "version": {
      "var_param": "version"
    },
    "input": {
      "var_param": "input_"
    },
    "directions": {
      "var_param": "directions"
    },
    "output": {
      "var_param": "output"
    }
  }
}